witss/__init__.py
witss/signature/__init__.py
witss/signature/base.py
witss/signature/compute.py
witss/signature/semiring.py
witss/signature/weighting.py
witss/words/__init__.py
witss/words/generate.py
witss/words/word.py
witss-1.0.0.dist-info/LICENSE
witss-1.0.0.dist-info/METADATA
witss-1.0.0.dist-info/WHEEL
witss-1.0.0.dist-info/RECORD
